elderlang/__init__.py
elderlang/__main__.py
elderlang/elderlang.py
elderlang-0.0.4.dist-info/METADATA
elderlang-0.0.4.dist-info/WHEEL
elderlang-0.0.4.dist-info/entry_points.txt
elderlang-0.0.4.dist-info/top_level.txt
elderlang-0.0.4.dist-info/RECORD
