Metadata-Version: 2.1
Name: elderlang
Version: 0.0.4
Summary: The Elder Language
Home-page: https://github.com/elderlang/elderlang
Author: eons
Author-email: support@eons.llc
Project-URL: Bug Tracker, https://github.com/elderlang/elderlang/issues
Classifier: Programming Language :: Python :: 3
Classifier: License :: OSI Approved :: MIT License
Classifier: Operating System :: OS Independent
Requires-Python: >=3.7
Requires-Dist: jsonpickle
Requires-Dist: eons
